web_poet/__init__.py
web_poet/_base.py
web_poet/annotated.py
web_poet/example.py
web_poet/fields.py
web_poet/mixins.py
web_poet/pages.py
web_poet/py.typed
web_poet/requests.py
web_poet/rules.py
web_poet/utils.py
web_poet/exceptions/__init__.py
web_poet/exceptions/core.py
web_poet/exceptions/http.py
web_poet/page_inputs/__init__.py
web_poet/page_inputs/browser.py
web_poet/page_inputs/client.py
web_poet/page_inputs/http.py
web_poet/page_inputs/page_params.py
web_poet/page_inputs/response.py
web_poet/page_inputs/stats.py
web_poet/page_inputs/url.py
web_poet/serialization/__init__.py
web_poet/serialization/api.py
web_poet/serialization/functions.py
web_poet/serialization/utils.py
web_poet/testing/__init__.py
web_poet/testing/__main__.py
web_poet/testing/exceptions.py
web_poet/testing/fixture.py
web_poet/testing/itemadapter.py
web_poet/testing/pytest.py
web_poet/testing/utils.py
web_poet-0.22.0.dist-info/licenses/LICENSE
web_poet-0.22.0.dist-info/METADATA
web_poet-0.22.0.dist-info/WHEEL
web_poet-0.22.0.dist-info/entry_points.txt
web_poet-0.22.0.dist-info/top_level.txt
web_poet-0.22.0.dist-info/RECORD
