Metadata-Version: 2.4
Name: web-poet
Version: 0.22.0
Summary: Zyte's Page Object pattern for web scraping
Home-page: https://github.com/scrapinghub/web-poet
Author: Zyte Group Ltd
Author-email: opensource@zyte.com
Classifier: Development Status :: 3 - Alpha
Classifier: Intended Audience :: Developers
Classifier: License :: OSI Approved :: BSD License
Classifier: Natural Language :: English
Classifier: Operating System :: OS Independent
Classifier: Programming Language :: Python :: 3
Classifier: Programming Language :: Python :: 3.9
Classifier: Programming Language :: Python :: 3.10
Classifier: Programming Language :: Python :: 3.11
Classifier: Programming Language :: Python :: 3.12
Classifier: Programming Language :: Python :: 3.13
Classifier: Programming Language :: Python :: 3.14
License-File: LICENSE
Requires-Dist: attrs>=21.3.0
Requires-Dist: parsel>=1.5.0
Requires-Dist: url-matcher>=0.4.0
Requires-Dist: multidict>=0.5.0
Requires-Dist: w3lib>=1.22.0
Requires-Dist: async-lru>=1.0.3
Requires-Dist: itemadapter>=0.8.0
Requires-Dist: andi>=0.5.0
Requires-Dist: python-dateutil>=2.7.0
Requires-Dist: time-machine>=2.7.1
Requires-Dist: packaging>=20.0
Dynamic: author
Dynamic: author-email
Dynamic: classifier
Dynamic: description
Dynamic: description-content-type
Dynamic: home-page
Dynamic: license-file
Dynamic: requires-dist
Dynamic: summary
